alibabacloud_paifeaturestore20230621/__init__.py
alibabacloud_paifeaturestore20230621/client.py
alibabacloud_paifeaturestore20230621/models/__init__.py
alibabacloud_paifeaturestore20230621/models/_check_instance_datasource_request.py
alibabacloud_paifeaturestore20230621/models/_check_instance_datasource_response.py
alibabacloud_paifeaturestore20230621/models/_check_instance_datasource_response_body.py
alibabacloud_paifeaturestore20230621/models/_check_model_feature_fgfeature_response.py
alibabacloud_paifeaturestore20230621/models/_check_model_feature_fgfeature_response_body.py
alibabacloud_paifeaturestore20230621/models/_create_datasource_request.py
alibabacloud_paifeaturestore20230621/models/_create_datasource_response.py
alibabacloud_paifeaturestore20230621/models/_create_datasource_response_body.py
alibabacloud_paifeaturestore20230621/models/_create_feature_entity_request.py
alibabacloud_paifeaturestore20230621/models/_create_feature_entity_response.py
alibabacloud_paifeaturestore20230621/models/_create_feature_entity_response_body.py
alibabacloud_paifeaturestore20230621/models/_create_feature_view_request.py
alibabacloud_paifeaturestore20230621/models/_create_feature_view_response.py
alibabacloud_paifeaturestore20230621/models/_create_feature_view_response_body.py
alibabacloud_paifeaturestore20230621/models/_create_instance_request.py
alibabacloud_paifeaturestore20230621/models/_create_instance_response.py
alibabacloud_paifeaturestore20230621/models/_create_instance_response_body.py
alibabacloud_paifeaturestore20230621/models/_create_label_table_request.py
alibabacloud_paifeaturestore20230621/models/_create_label_table_response.py
alibabacloud_paifeaturestore20230621/models/_create_label_table_response_body.py
alibabacloud_paifeaturestore20230621/models/_create_llmconfig_request.py
alibabacloud_paifeaturestore20230621/models/_create_llmconfig_response.py
alibabacloud_paifeaturestore20230621/models/_create_llmconfig_response_body.py
alibabacloud_paifeaturestore20230621-6.0.7.dist-info/LICENSE
alibabacloud_paifeaturestore20230621-6.0.7.dist-info/METADATA
alibabacloud_paifeaturestore20230621-6.0.7.dist-info/WHEEL
alibabacloud_paifeaturestore20230621-6.0.7.dist-info/top_level.txt
alibabacloud_paifeaturestore20230621-6.0.7.dist-info/RECORD
